aiobservable/__init__.py
aiobservable/abstract.py
aiobservable/observable.py
aiobservable/types.py
aiobservable-0.2.2.dist-info/LICENSE
aiobservable-0.2.2.dist-info/METADATA
aiobservable-0.2.2.dist-info/WHEEL
aiobservable-0.2.2.dist-info/top_level.txt
aiobservable-0.2.2.dist-info/RECORD
