Metadata-Version: 2.1
Name: aiobservable
Version: 0.2.2
Summary: UNKNOWN
Home-page: https://github.com/gieseladev/aiobservable
Author: Giesela Inc.
Author-email: team@giesela.dev
License: MIT
Platform: UNKNOWN
Requires-Python: >=3.6
